scm_config/__init__.py
scm_config/cli.py
scm_config/default_config.py
scm_config/defaults.py
scm_config/main.py
scm_config-1.0.0.dist-info/entry_points.txt
scm_config-1.0.0.dist-info/WHEEL
scm_config-1.0.0.dist-info/METADATA
scm_config-1.0.0.dist-info/RECORD
