Metadata-Version: 2.1
Name: scm-config
Version: 1.0.0
Summary: self configuration management written in Python
Home-page: https://github.com/Sai-Repalle/scm_project
License: MIT
Keywords: config,markdown,lint
Author: Sai Repalle
Author-email: n.repalle85@gmail.com
Requires-Python: >=3.6,<4.0
Classifier: Environment :: Console
Classifier: License :: OSI Approved :: MIT License
Classifier: Operating System :: POSIX :: Linux
Classifier: Programming Language :: Python :: 3
Classifier: Programming Language :: Python :: 3.10
Classifier: Programming Language :: Python :: 3.6
Classifier: Programming Language :: Python :: 3.7
Classifier: Programming Language :: Python :: 3.8
Classifier: Programming Language :: Python :: 3.9
Requires-Dist: colorama (>=0.4.4,<0.5.0)
Requires-Dist: deepdiff (>=5.7.0,<6.0.0)
Requires-Dist: dynaconf (>=3.1.5,<4.0.0)
Requires-Dist: ordered-set (>=4.0.2,<5.0.0)
Requires-Dist: pytest (>=7.0.1,<8.0.0)
Requires-Dist: typer (>=0.4.1,<0.5.0)
Requires-Dist: wheel (>=0.37.1,<0.38.0)
Project-URL: Repository, https://github.com/Sai-Repalle/scm_project
